matoolkit/__init__.py
matoolkit/draw_arrow.py
matoolkit/multiple_linecharts.py
matoolkit/tile_map.py
matoolkit/tests/__init__.py
matoolkit/tests/test_draw_arrow.py
matoolkit/tests/test_multiple_linecharts.py
matoolkit/utils/__init__.py
matoolkit/utils/region_properties.py
matoolkit/utils/text_positions.py
matoolkit/utils/valid_highlight_text.py
matoolkit-0.1.2.dist-info/LICENSE
matoolkit-0.1.2.dist-info/METADATA
matoolkit-0.1.2.dist-info/WHEEL
matoolkit-0.1.2.dist-info/top_level.txt
matoolkit-0.1.2.dist-info/RECORD
