Metadata-Version: 2.1
Name: matoolkit
Version: 0.1.2
Summary: A toolkit for chart creation in matplotlib
Home-page: http://www.barberjoseph.com
Author: Joseph Barbier
Author-email: Joseph Barbier <joseph.barbierdarnal@gmail.com>
Project-URL: Homepage, https://github.com/pypa/sampleproject
Project-URL: Issues, https://github.com/pypa/sampleproject/issues
Classifier: Programming Language :: Python :: 3
Classifier: License :: OSI Approved :: MIT License
Classifier: Operating System :: OS Independent
Requires-Python: >=3.8
License-File: LICENSE
Requires-Dist: pandas
Requires-Dist: highlight-text
Requires-Dist: matplotlib
Requires-Dist: pytest
